streamlit_label_graph/__init__.py
streamlit_label_graph/__main__.py
streamlit_label_graph/frontend/index.html
streamlit_label_graph/frontend/main.js
streamlit_label_graph/frontend/streamlit-component-lib.js
streamlit_label_graph/frontend/style.css
streamlit_label_graph-0.1.2.dist-info/LICENSE
streamlit_label_graph-0.1.2.dist-info/METADATA
streamlit_label_graph-0.1.2.dist-info/WHEEL
streamlit_label_graph-0.1.2.dist-info/top_level.txt
streamlit_label_graph-0.1.2.dist-info/RECORD
