Metadata-Version: 2.1
Name: streamlit-label-graph
Version: 0.1.2
Summary: Plotly graph for labelling timeserie data
Author: Mikkel Jans
Author-email: mikkeljans@gmail.com
Requires-Python: >=3.7
License-File: LICENSE
Requires-Dist: streamlit (>=1.2)
Requires-Dist: jinja2
Requires-Dist: plotly
